7_sim_debounce/state_machine_Moore.v
module state_machine_Moore #(
    parameter CLK_ITER_WIDTH = 20,
    parameter CLK_ITER_MAX   = 600000 - 1   //0.1Hz, factor of 2 from "clk_div <= ~clk_div"
)(
    input               clk,        //12MHz clock
    input               rstInput,
    input               goInput, 
    output  reg [3:0]   led,
    output  reg         doneSig
);
//////////////////////////////////////////////////////////////////////////////////////////////
    wire    rst;
    wire    go;
    assign  rst = rstInput;
    assign  go  = goInput;

    reg [1:0]   state;
    localparam  STATE_IDLE = 2'd0;
    localparam  STATE_PROC = 2'd1;
    localparam  STATE_DONE = 2'd2;

    reg                     clk_div;
    reg [CLK_ITER_WIDTH:0]  clk_iter;
//////////////////////////////////////////////////////////////////////////////////////////////
//clock handling
    always @ (posedge rst or posedge clk) begin
        if (rst == 1'b1) begin
            clk_iter <= 20'b0;
            clk_div  <= 0;
        end else if (clk_iter == CLK_ITER_MAX) begin
            clk_iter <= 20'b0;
            clk_div  <= ~clk_div;
        end else begin 
            clk_iter <= clk_iter + 1'b1;
        end
    end
//state handling
    always @ (posedge rst or posedge clk_div) begin
        if (rst == 1'b1) begin
            state <= STATE_IDLE;
        end else begin
            case(state)
                STATE_IDLE: begin
                    if (go == 1'b1) begin
                        state <= STATE_PROC;
                    end
                end                
                STATE_PROC: state <= STATE_DONE;
                STATE_DONE: begin
                    if (go == 1'b0) begin
                        state <= STATE_IDLE;
                    end
                end
                default: state <= STATE_IDLE;
            endcase
        end 
    end
//LED handling
    always @ (posedge rst or posedge clk_div) begin
        if (rst == 1'b1) begin
            led <= 4'b0;
        // enough time to catch the following before state goes to STATE_DONE?
        // note that mixing led with blocking/unblocking will create problem when combining
        //rst/go input  
        end else if (state == STATE_PROC) begin
            led <= led + 1'b1; 
        end 
    end
    always @ ( * ) begin
        if (state == STATE_DONE) begin
            doneSig = 1'b1;                     //blocking assignment
        end else begin
            doneSig = 1'b0;                     //blocking assignment
        end
    end
endmodule
//////////////////////////////////////////////////////////////////////////////////////////////

7_sim_debounce/main_tb.v
`timescale 1 ns / 10 ps              // set simulated unit / precision

module main_tb();
    wire [3:0]  led;
    wire        done_sig;
    reg clk = 0;
    reg rst = 0;
    reg go  = 0;
    localparam SIM_DURATION = 250000;    // in unit of timescale
    integer debounceIter = 0;

    // simulation keeps on running the following
    always begin
        #41.667                     //delay by, 1/(2*41.67*1ns) ~ 12MHz of IceStick, round to precision
        clk = ~clk;
    end

    // unit under test (uut), wait for 3/12MHz ~ 0.25us to avoid debouncing
    state_machine_Moore #(.CLK_ITER_WIDTH(2), .CLK_ITER_MAX(3 - 1)) uut(
        .clk(clk),
        .rstInput(rst),
        .goInput(go),
        .led(led),
        .doneSig(done_sig)
    );

    // pulse reset high at beginning
    initial begin
        #10             //delay by 10*1ns = 10ns 
        rst = 1'b1;
        #1              //delay by 1*1ns = 1ns 
        rst = 1'b0;
    end

    // pressing go periodically
    always begin
        #10000           //delay by 10000*1ns = 10.0us 
        go = 1'b1;
        #1000            //lasting 1000*1ns = 1.0us 
        go = 1'b1;
        for (debounceIter = 0; debounceIter < 32; debounceIter = debounceIter + 1) begin
            #1
            go = $urandom%2;
        end 
        #1
        go = 1'b0;
    end

    // output file
    initial begin
        $dumpfile("main_tb.vcd");
        $dumpvars(0, main_tb);     //0 verbosity means max verbosity
        #(SIM_DURATION)
        $display("End of Sim.");
        $finish;
    end
endmodule

7_sim_debounce/main_tb.vcd
$date
	Sun Jul 28 22:41:39 2024
$end
$version
	Icarus Verilog
$end
$timescale
	1ps
$end
$scope module main_tb $end
$var wire 4 ! led [3:0] $end
$var wire 1 " done_sig $end
$var parameter 32 # SIM_DURATION $end
$var reg 1 $ clk $end
$var reg 1 % go $end
$var reg 1 & rst $end
$var integer 32 ' debounceIter [31:0] $end
$scope module uut $end
$var wire 1 $ clk $end
$var wire 1 ( go $end
$var wire 1 % goInput $end
$var wire 1 ) rst $end
$var wire 1 & rstInput $end
$var parameter 33 * CLK_ITER_MAX $end
$var parameter 32 + CLK_ITER_WIDTH $end
$var parameter 2 , STATE_DONE $end
$var parameter 2 - STATE_IDLE $end
$var parameter 2 . STATE_PROC $end
$var reg 1 / clk_div $end
$var reg 3 0 clk_iter [2:0] $end
$var reg 1 " doneSig $end
$var reg 4 1 led [3:0] $end
$var reg 2 2 state [1:0] $end
$upscope $end
$upscope $end
$enddefinitions $end
$comment Show the parameter values. $end
$dumpall
b1 .
b0 -
b10 ,
b10 +
b10 *
b111101000010010000 #
$end
#0
$dumpvars
bx 2
bx 1
bx 0
x/
0)
0(
b0 '
0&
0%
0$
x"
bx !
$end
#10000
0"
b0 2
b0 !
b0 1
0/
b0 0
1)
1&
#11000
0)
0&
#41670
b1 0
1$
#83340
0$
#125010
b10 0
1$
#166680
0$
#208350
1/
b0 0
1$
#250020
0$
#291690
b1 0
1$
#333360
0$
#375030
b10 0
1$
#416700
0$
#458370
0/
b0 0
1$
#500040
0$
#541710
b1 0
1$
#583380
0$
#625050
b10 0
1$
#666720
0$
#708390
1/
b0 0
1$
#750060
0$
#791730
b1 0
1$
#833400
0$
#875070
b10 0
1$
#916740
0$
#958410
0/
b0 0
1$
#1000080
0$
#1041750
b1 0
1$
#1083420
0$
#1125090
b10 0
1$
#1166760
0$
#1208430
1/
b0 0
1$
#1250100
0$
#1291770
b1 0
1$
#1333440
0$
#1375110
b10 0
1$
#1416780
0$
#1458450
0/
b0 0
1$
#1500120
0$
#1541790
b1 0
1$
#1583460
0$
#1625130
b10 0
1$
#1666800
0$
#1708470
1/
b0 0
1$
#1750140
0$
#1791810
b1 0
1$
#1833480
0$
#1875150
b10 0
1$
#1916820
0$
#1958490
0/
b0 0
1$
#2000160
0$
#2041830
b1 0
1$
#2083500
0$
#2125170
b10 0
1$
#2166840
0$
#2208510
1/
b0 0
1$
#2250180
0$
#2291850
b1 0
1$
#2333520
0$
#2375190
b10 0
1$
#2416860
0$
#2458530
0/
b0 0
1$
#2500200
0$
#2541870
b1 0
1$
#2583540
0$
#2625210
b10 0
1$
#2666880
0$
#2708550
1/
b0 0
1$
#2750220
0$
#2791890
b1 0
1$
#2833560
0$
#2875230
b10 0
1$
#2916900
0$
#2958570
0/
b0 0
1$
#3000240
0$
#3041910
b1 0
1$
#3083580
0$
#3125250
b10 0
1$
#3166920
0$
#3208590
1/
b0 0
1$
#3250260
0$
#3291930
b1 0
1$
#3333600
0$
#3375270
b10 0
1$
#3416940
0$
#3458610
0/
b0 0
1$
#3500280
0$
#3541950
b1 0
1$
#3583620
0$
#3625290
b10 0
1$
#3666960
0$
#3708630
1/
b0 0
1$
#3750300
0$
#3791970
b1 0
1$
#3833640
0$
#3875310
b10 0
1$
#3916980
0$
#3958650
0/
b0 0
1$
#4000320
0$
#4041990
b1 0
1$
#4083660
0$
#4125330
b10 0
1$
#4167000
0$
#4208670
1/
b0 0
1$
#4250340
0$
#4292010
b1 0
1$
#4333680
0$
#4375350
b10 0
1$
#4417020
0$
#4458690
0/
b0 0
1$
#4500360
0$
#4542030
b1 0
1$
#4583700
0$
#4625370
b10 0
1$
#4667040
0$
#4708710
1/
b0 0
1$
#4750380
0$
#4792050
b1 0
1$
#4833720
0$
#4875390
b10 0
1$
#4917060
0$
#4958730
0/
b0 0
1$
#5000400
0$
#5042070
b1 0
1$
#5083740
0$
#5125410
b10 0
1$
#5167080
0$
#5208750
1/
b0 0
1$
#5250420
0$
#5292090
b1 0
1$
#5333760
0$
#5375430
b10 0
1$
#5417100
0$
#5458770
0/
b0 0
1$
#5500440
0$
#5542110
b1 0
1$
#5583780
0$
#5625450
b10 0
1$
#5667120
0$
#5708790
1/
b0 0
1$
#5750460
0$
#5792130
b1 0
1$
#5833800
0$
#5875470
b10 0
1$
#5917140
0$
#5958810
0/
b0 0
1$
#6000480
0$
#6042150
b1 0
1$
#6083820
0$
#6125490
b10 0
1$
#6167160
0$
#6208830
1/
b0 0
1$
#6250500
0$
#6292170
b1 0
1$
#6333840
0$
#6375510
b10 0
1$
#6417180
0$
#6458850
0/
b0 0
1$
#6500520
0$
#6542190
b1 0
1$
#6583860
0$
#6625530
b10 0
1$
#6667200
0$
#6708870
1/
b0 0
1$
#6750540
0$
#6792210
b1 0
1$
#6833880
0$
#6875550
b10 0
1$
#6917220
0$
#6958890
0/
b0 0
1$
#7000560
0$
#7042230
b1 0
1$
#7083900
0$
#7125570
b10 0
1$
#7167240
0$
#7208910
1/
b0 0
1$
#7250580
0$
#7292250
b1 0
1$
#7333920
0$
#7375590
b10 0
1$
#7417260
0$
#7458930
0/
b0 0
1$
#7500600
0$
#7542270
b1 0
1$
#7583940
0$
#7625610
b10 0
1$
#7667280
0$
#7708950
1/
b0 0
1$
#7750620
0$
#7792290
b1 0
1$
#7833960
0$
#7875630
b10 0
1$
#7917300
0$
#7958970
0/
b0 0
1$
#8000640
0$
#8042310
b1 0
1$
#8083980
0$
#8125650
b10 0
1$
#8167320
0$
#8208990
1/
b0 0
1$
#8250660
0$
#8292330
b1 0
1$
#8334000
0$
#8375670
b10 0
1$
#8417340
0$
#8459010
0/
b0 0
1$
#8500680
0$
#8542350
b1 0
1$
#8584020
0$
#8625690
b10 0
1$
#8667360
0$
#8709030
1/
b0 0
1$
#8750700
0$
#8792370
b1 0
1$
#8834040
0$
#8875710
b10 0
1$
#8917380
0$
#8959050
0/
b0 0
1$
#9000720
0$
#9042390
b1 0
1$
#9084060
0$
#9125730
b10 0
1$
#9167400
0$
#9209070
1/
b0 0
1$
#9250740
0$
#9292410
b1 0
1$
#9334080
0$
#9375750
b10 0
1$
#9417420
0$
#9459090
0/
b0 0
1$
#9500760
0$
#9542430
b1 0
1$
#9584100
0$
#9625770
b10 0
1$
#9667440
0$
#9709110
1/
b0 0
1$
#9750780
0$
#9792450
b1 0
1$
#9834120
0$
#9875790
b10 0
1$
#9917460
0$
#9959130
0/
b0 0
1$
#10000000
1(
1%
#10000800
0$
#10042470
b1 0
1$
#10084140
0$
#10125810
b10 0
1$
#10167480
0$
#10209150
b1 2
1/
b0 0
1$
#10250820
0$
#10292490
b1 0
1$
#10334160
0$
#10375830
b10 0
1$
#10417500
0$
#10459170
0/
b0 0
1$
#10500840
0$
#10542510
b1 0
1$
#10584180
0$
#10625850
b10 0
1$
#10667520
0$
#10709190
1"
b10 2
b1 !
b1 1
1/
b0 0
1$
#10750860
0$
#10792530
b1 0
1$
#10834200
0$
#10875870
b10 0
1$
#10917540
0$
#10959210
0/
b0 0
1$
#11000880
0$
#11001000
b1 '
0(
0%
#11002000
b10 '
1(
1%
#11003000
b11 '
#11004000
b100 '
#11005000
b101 '
#11006000
b110 '
#11007000
b111 '
#11008000
b1000 '
0(
0%
#11009000
b1001 '
1(
1%
#11010000
b1010 '
#11011000
b1011 '
0(
0%
#11012000
b1100 '
1(
1%
#11013000
b1101 '
#11014000
b1110 '
0(
0%
#11015000
b1111 '
1(
1%
#11016000
b10000 '
0(
0%
#11017000
b10001 '
1(
1%
#11018000
b10010 '
0(
0%
#11019000
b10011 '
1(
1%
#11020000
b10100 '
#11021000
b10101 '
0(
0%
#11022000
b10110 '
1(
1%
#11023000
b10111 '
0(
0%
#11024000
b11000 '
#11025000
b11001 '
#11026000
b11010 '
1(
1%
#11027000
b11011 '
0(
0%
#11028000
b11100 '
1(
1%
#11029000
b11101 '
#11030000
b11110 '
#11031000
b11111 '
#11032000
b100000 '
0(
0%
#11042550
b1 0
1$
#11084220
0$
#11125890
b10 0
1$
#11167560
0$
#11209230
0"
b0 2
1/
b0 0
1$
#11250900
0$
#11292570
b1 0
1$
#11334240
0$
#11375910
b10 0
1$
#11417580
0$
#11459250
0/
b0 0
1$
#11500920
0$
#11542590
b1 0
1$
#11584260
0$
#11625930
b10 0
1$
#11667600
0$
#11709270
1/
b0 0
1$
#11750940
0$
#11792610
b1 0
1$
#11834280
0$
#11875950
b10 0
1$
#11917620
0$
#11959290
0/
b0 0
1$
#12000960
0$
#12042630
b1 0
1$
#12084300
0$
#12125970
b10 0
1$
#12167640
0$
#12209310
1/
b0 0
1$
#12250980
0$
#12292650
b1 0
1$
#12334320
0$
#12375990
b10 0
1$
#12417660
0$
#12459330
0/
b0 0
1$
#12501000
0$
#12542670
b1 0
1$
#12584340
0$
#12626010
b10 0
1$
#12667680
0$
#12709350
1/
b0 0
1$
#12751020
0$
#12792690
b1 0
1$
#12834360
0$
#12876030
b10 0
1$
#12917700
0$
#12959370
0/
b0 0
1$
#13001040
0$
#13042710
b1 0
1$
#13084380
0$
#13126050
b10 0
1$
#13167720
0$
#13209390
1/
b0 0
1$
#13251060
0$
#13292730
b1 0
1$
#13334400
0$
#13376070
b10 0
1$
#13417740
0$
#13459410
0/
b0 0
1$
#13501080
0$
#13542750
b1 0
1$
#13584420
0$
#13626090
b10 0
1$
#13667760
0$
#13709430
1/
b0 0
1$
#13751100
0$
#13792770
b1 0
1$
#13834440
0$
#13876110
b10 0
1$
#13917780
0$
#13959450
0/
b0 0
1$
#14001120
0$
#14042790
b1 0
1$
#14084460
0$
#14126130
b10 0
1$
#14167800
0$
#14209470
1/
b0 0
1$
#14251140
0$
#14292810
b1 0
1$
#14334480
0$
#14376150
b10 0
1$
#14417820
0$
#14459490
0/
b0 0
1$
#14501160
0$
#14542830
b1 0
1$
#14584500
0$
#14626170
b10 0
1$
#14667840
0$
#14709510
1/
b0 0
1$
#14751180
0$
#14792850
b1 0
1$
#14834520
0$
#14876190
b10 0
1$
#14917860
0$
#14959530
0/
b0 0
1$
#15001200
0$
#15042870
b1 0
1$
#15084540
0$
#15126210
b10 0
1$
#15167880
0$
#15209550
1/
b0 0
1$
#15251220
0$
#15292890
b1 0
1$
#15334560
0$
#15376230
b10 0
1$
#15417900
0$
#15459570
0/
b0 0
1$
#15501240
0$
#15542910
b1 0
1$
#15584580
0$
#15626250
b10 0
1$
#15667920
0$
#15709590
1/
b0 0
1$
#15751260
0$
#15792930
b1 0
1$
#15834600
0$
#15876270
b10 0
1$
#15917940
0$
#15959610
0/
b0 0
1$
#16001280
0$
#16042950
b1 0
1$
#16084620
0$
#16126290
b10 0
1$
#16167960
0$
#16209630
1/
b0 0
1$
#16251300
0$
#16292970
b1 0
1$
#16334640
0$
#16376310
b10 0
1$
#16417980
0$
#16459650
0/
b0 0
1$
#16501320
0$
#16542990
b1 0
1$
#16584660
0$
#16626330
b10 0
1$
#16668000
0$
#16709670
1/
b0 0
1$
#16751340
0$
#16793010
b1 0
1$
#16834680
0$
#16876350
b10 0
1$
#16918020
0$
#16959690
0/
b0 0
1$
#17001360
0$
#17043030
b1 0
1$
#17084700
0$
#17126370
b10 0
1$
#17168040
0$
#17209710
1/
b0 0
1$
#17251380
0$
#17293050
b1 0
1$
#17334720
0$
#17376390
b10 0
1$
#17418060
0$
#17459730
0/
b0 0
1$
#17501400
0$
#17543070
b1 0
1$
#17584740
0$
#17626410
b10 0
1$
#17668080
0$
#17709750
1/
b0 0
1$
#17751420
0$
#17793090
b1 0
1$
#17834760
0$
#17876430
b10 0
1$
#17918100
0$
#17959770
0/
b0 0
1$
#18001440
0$
#18043110
b1 0
1$
#18084780
0$
#18126450
b10 0
1$
#18168120
0$
#18209790
1/
b0 0
1$
#18251460
0$
#18293130
b1 0
1$
#18334800
0$
#18376470
b10 0
1$
#18418140
0$
#18459810
0/
b0 0
1$
#18501480
0$
#18543150
b1 0
1$
#18584820
0$
#18626490
b10 0
1$
#18668160
0$
#18709830
1/
b0 0
1$
#18751500
0$
#18793170
b1 0
1$
#18834840
0$
#18876510
b10 0
1$
#18918180
0$
#18959850
0/
b0 0
1$
#19001520
0$
#19043190
b1 0
1$
#19084860
0$
#19126530
b10 0
1$
#19168200
0$
#19209870
1/
b0 0
1$
#19251540
0$
#19293210
b1 0
1$
#19334880
0$
#19376550
b10 0
1$
#19418220
0$
#19459890
0/
b0 0
1$
#19501560
0$
#19543230
b1 0
1$
#19584900
0$
#19626570
b10 0
1$
#19668240
0$
#19709910
1/
b0 0
1$
#19751580
0$
#19793250
b1 0
1$
#19834920
0$
#19876590
b10 0
1$
#19918260
0$
#19959930
0/
b0 0
1$
#20001600
0$
#20043270
b1 0
1$
#20084940
0$
#20126610
b10 0
1$
#20168280
0$
#20209950
1/
b0 0
1$
#20251620
0$
#20293290
b1 0
1$
#20334960
0$
#20376630
b10 0
1$
#20418300
0$
#20459970
0/
b0 0
1$
#20501640
0$
#20543310
b1 0
1$
#20584980
0$
#20626650
b10 0
1$
#20668320
0$
#20709990
1/
b0 0
1$
#20751660
0$
#20793330
b1 0
1$
#20835000
0$
#20876670
b10 0
1$
#20918340
0$
#20960010
0/
b0 0
1$
#21001680
0$
#21033000
1(
1%
#21043350
b1 0
1$
#21085020
0$
#21126690
b10 0
1$
#21168360
0$
#21210030
b1 2
1/
b0 0
1$
#21251700
0$
#21293370
b1 0
1$
#21335040
0$
#21376710
b10 0
1$
#21418380
0$
#21460050
0/
b0 0
1$
#21501720
0$
#21543390
b1 0
1$
#21585060
0$
#21626730
b10 0
1$
#21668400
0$
#21710070
1"
b10 2
b10 !
b10 1
1/
b0 0
1$
#21751740
0$
#21793410
b1 0
1$
#21835080
0$
#21876750
b10 0
1$
#21918420
0$
#21960090
0/
b0 0
1$
#22001760
0$
#22033000
b0 '
#22034000
b1 '
0(
0%
#22035000
b10 '
#22036000
b11 '
#22037000
b100 '
1(
1%
#22038000
b101 '
0(
0%
#22039000
b110 '
1(
1%
#22040000
b111 '
#22041000
b1000 '
#22042000
b1001 '
#22043000
b1010 '
#22043430
b1 0
1$
#22044000
b1011 '
0(
0%
#22045000
b1100 '
#22046000
b1101 '
1(
1%
#22047000
b1110 '
#22048000
b1111 '
#22049000
b10000 '
0(
0%
#22050000
b10001 '
#22051000
b10010 '
#22052000
b10011 '
#22053000
b10100 '
#22054000
b10101 '
1(
1%
#22055000
b10110 '
0(
0%
#22056000
b10111 '
#22057000
b11000 '
1(
1%
#22058000
b11001 '
#22059000
b11010 '
0(
0%
#22060000
b11011 '
#22061000
b11100 '
#22062000
b11101 '
#22063000
b11110 '
#22064000
b11111 '
1(
1%
#22065000
b100000 '
#22066000
0(
0%
#22085100
0$
#22126770
b10 0
1$
#22168440
0$
#22210110
0"
b0 2
1/
b0 0
1$
#22251780
0$
#22293450
b1 0
1$
#22335120
0$
#22376790
b10 0
1$
#22418460
0$
#22460130
0/
b0 0
1$
#22501800
0$
#22543470
b1 0
1$
#22585140
0$
#22626810
b10 0
1$
#22668480
0$
#22710150
1/
b0 0
1$
#22751820
0$
#22793490
b1 0
1$
#22835160
0$
#22876830
b10 0
1$
#22918500
0$
#22960170
0/
b0 0
1$
#23001840
0$
#23043510
b1 0
1$
#23085180
0$
#23126850
b10 0
1$
#23168520
0$
#23210190
1/
b0 0
1$
#23251860
0$
#23293530
b1 0
1$
#23335200
0$
#23376870
b10 0
1$
#23418540
0$
#23460210
0/
b0 0
1$
#23501880
0$
#23543550
b1 0
1$
#23585220
0$
#23626890
b10 0
1$
#23668560
0$
#23710230
1/
b0 0
1$
#23751900
0$
#23793570
b1 0
1$
#23835240
0$
#23876910
b10 0
1$
#23918580
0$
#23960250
0/
b0 0
1$
#24001920
0$
#24043590
b1 0
1$
#24085260
0$
#24126930
b10 0
1$
#24168600
0$
#24210270
1/
b0 0
1$
#24251940
0$
#24293610
b1 0
1$
#24335280
0$
#24376950
b10 0
1$
#24418620
0$
#24460290
0/
b0 0
1$
#24501960
0$
#24543630
b1 0
1$
#24585300
0$
#24626970
b10 0
1$
#24668640
0$
#24710310
1/
b0 0
1$
#24751980
0$
#24793650
b1 0
1$
#24835320
0$
#24876990
b10 0
1$
#24918660
0$
#24960330
0/
b0 0
1$
#25002000
0$
#25043670
b1 0
1$
#25085340
0$
#25127010
b10 0
1$
#25168680
0$
#25210350
1/
b0 0
1$
#25252020
0$
#25293690
b1 0
1$
#25335360
0$
#25377030
b10 0
1$
#25418700
0$
#25460370
0/
b0 0
1$
#25502040
0$
#25543710
b1 0
1$
#25585380
0$
#25627050
b10 0
1$
#25668720
0$
#25710390
1/
b0 0
1$
#25752060
0$
#25793730
b1 0
1$
#25835400
0$
#25877070
b10 0
1$
#25918740
0$
#25960410
0/
b0 0
1$
#26002080
0$
#26043750
b1 0
1$
#26085420
0$
#26127090
b10 0
1$
#26168760
0$
#26210430
1/
b0 0
1$
#26252100
0$
#26293770
b1 0
1$
#26335440
0$
#26377110
b10 0
1$
#26418780
0$
#26460450
0/
b0 0
1$
#26502120
0$
#26543790
b1 0
1$
#26585460
0$
#26627130
b10 0
1$
#26668800
0$
#26710470
1/
b0 0
1$
#26752140
0$
#26793810
b1 0
1$
#26835480
0$
#26877150
b10 0
1$
#26918820
0$
#26960490
0/
b0 0
1$
#27002160
0$
#27043830
b1 0
1$
#27085500
0$
#27127170
b10 0
1$
#27168840
0$
#27210510
1/
b0 0
1$
#27252180
0$
#27293850
b1 0
1$
#27335520
0$
#27377190
b10 0
1$
#27418860
0$
#27460530
0/
b0 0
1$
#27502200
0$
#27543870
b1 0
1$
#27585540
0$
#27627210
b10 0
1$
#27668880
0$
#27710550
1/
b0 0
1$
#27752220
0$
#27793890
b1 0
1$
#27835560
0$
#27877230
b10 0
1$
#27918900
0$
#27960570
0/
b0 0
1$
#28002240
0$
#28043910
b1 0
1$
#28085580
0$
#28127250
b10 0
1$
#28168920
0$
#28210590
1/
b0 0
1$
#28252260
0$
#28293930
b1 0
1$
#28335600
0$
#28377270
b10 0
1$
#28418940
0$
#28460610
0/
b0 0
1$
#28502280
0$
#28543950
b1 0
1$
#28585620
0$
#28627290
b10 0
1$
#28668960
0$
#28710630
1/
b0 0
1$
#28752300
0$
#28793970
b1 0
1$
#28835640
0$
#28877310
b10 0
1$
#28918980
0$
#28960650
0/
b0 0
1$
#29002320
0$
#29043990
b1 0
1$
#29085660
0$
#29127330
b10 0
1$
#29169000
0$
#29210670
1/
b0 0
1$
#29252340
0$
#29294010
b1 0
1$
#29335680
0$
#29377350
b10 0
1$
#29419020
0$
#29460690
0/
b0 0
1$
#29502360
0$
#29544030
b1 0
1$
#29585700
0$
#29627370
b10 0
1$
#29669040
0$
#29710710
1/
b0 0
1$
#29752380
0$
#29794050
b1 0
1$
#29835720
0$
#29877390
b10 0
1$
#29919060
0$
#29960730
0/
b0 0
1$
#30002400
0$
#30044070
b1 0
1$
#30085740
0$
#30127410
b10 0
1$
#30169080
0$
#30210750
1/
b0 0
1$
#30252420
0$
#30294090
b1 0
1$
#30335760
0$
#30377430
b10 0
1$
#30419100
0$
#30460770
0/
b0 0
1$
#30502440
0$
#30544110
b1 0
1$
#30585780
0$
#30627450
b10 0
1$
#30669120
0$
#30710790
1/
b0 0
1$
#30752460
0$
#30794130
b1 0
1$
#30835800
0$
#30877470
b10 0
1$
#30919140
0$
#30960810
0/
b0 0
1$
#31002480
0$
#31044150
b1 0
1$
#31085820
0$
#31127490
b10 0
1$
#31169160
0$
#31210830
1/
b0 0
1$
#31252500
0$
#31294170
b1 0
1$
#31335840
0$
#31377510
b10 0
1$
#31419180
0$
#31460850
0/
b0 0
1$
#31502520
0$
#31544190
b1 0
1$
#31585860
0$
#31627530
b10 0
1$
#31669200
0$
#31710870
1/
b0 0
1$
#31752540
0$
#31794210
b1 0
1$
#31835880
0$
#31877550
b10 0
1$
#31919220
0$
#31960890
0/
b0 0
1$
#32002560
0$
#32044230
b1 0
1$
#32066000
1(
1%
#32085900
0$
#32127570
b10 0
1$
#32169240
0$
#32210910
b1 2
1/
b0 0
1$
#32252580
0$
#32294250
b1 0
1$
#32335920
0$
#32377590
b10 0
1$
#32419260
0$
#32460930
0/
b0 0
1$
#32502600
0$
#32544270
b1 0
1$
#32585940
0$
#32627610
b10 0
1$
#32669280
0$
#32710950
1"
b10 2
b11 !
b11 1
1/
b0 0
1$
#32752620
0$
#32794290
b1 0
1$
#32835960
0$
#32877630
b10 0
1$
#32919300
0$
#32960970
0/
b0 0
1$
#33002640
0$
#33044310
b1 0
1$
#33066000
b0 '
#33067000
b1 '
#33068000
b10 '
#33069000
b11 '
#33070000
b100 '
0(
0%
#33071000
b101 '
#33072000
b110 '
1(
1%
#33073000
b111 '
#33074000
b1000 '
#33075000
b1001 '
0(
0%
#33076000
b1010 '
#33077000
b1011 '
1(
1%
#33078000
b1100 '
#33079000
b1101 '
0(
0%
#33080000
b1110 '
1(
1%
#33081000
b1111 '
#33082000
b10000 '
0(
0%
#33083000
b10001 '
1(
1%
#33084000
b10010 '
#33085000
b10011 '
#33085980
0$
#33086000
b10100 '
0(
0%
#33087000
b10101 '
1(
1%
#33088000
b10110 '
#33089000
b10111 '
0(
0%
#33090000
b11000 '
#33091000
b11001 '
#33092000
b11010 '
#33093000
b11011 '
1(
1%
#33094000
b11100 '
#33095000
b11101 '
0(
0%
#33096000
b11110 '
#33097000
b11111 '
1(
1%
#33098000
b100000 '
#33099000
0(
0%
#33127650
b10 0
1$
#33169320
0$
#33210990
0"
b0 2
1/
b0 0
1$
#33252660
0$
#33294330
b1 0
1$
#33336000
0$
#33377670
b10 0
1$
#33419340
0$
#33461010
0/
b0 0
1$
#33502680
0$
#33544350
b1 0
1$
#33586020
0$
#33627690
b10 0
1$
#33669360
0$
#33711030
1/
b0 0
1$
#33752700
0$
#33794370
b1 0
1$
#33836040
0$
#33877710
b10 0
1$
#33919380
0$
#33961050
0/
b0 0
1$
#34002720
0$
#34044390
b1 0
1$
#34086060
0$
#34127730
b10 0
1$
#34169400
0$
#34211070
1/
b0 0
1$
#34252740
0$
#34294410
b1 0
1$
#34336080
0$
#34377750
b10 0
1$
#34419420
0$
#34461090
0/
b0 0
1$
#34502760
0$
#34544430
b1 0
1$
#34586100
0$
#34627770
b10 0
1$
#34669440
0$
#34711110
1/
b0 0
1$
#34752780
0$
#34794450
b1 0
1$
#34836120
0$
#34877790
b10 0
1$
#34919460
0$
#34961130
0/
b0 0
1$
#35002800
0$
#35044470
b1 0
1$
#35086140
0$
#35127810
b10 0
1$
#35169480
0$
#35211150
1/
b0 0
1$
#35252820
0$
#35294490
b1 0
1$
#35336160
0$
#35377830
b10 0
1$
#35419500
0$
#35461170
0/
b0 0
1$
#35502840
0$
#35544510
b1 0
1$
#35586180
0$
#35627850
b10 0
1$
#35669520
0$
#35711190
1/
b0 0
1$
#35752860
0$
#35794530
b1 0
1$
#35836200
0$
#35877870
b10 0
1$
#35919540
0$
#35961210
0/
b0 0
1$
#36002880
0$
#36044550
b1 0
1$
#36086220
0$
#36127890
b10 0
1$
#36169560
0$
#36211230
1/
b0 0
1$
#36252900
0$
#36294570
b1 0
1$
#36336240
0$
#36377910
b10 0
1$
#36419580
0$
#36461250
0/
b0 0
1$
#36502920
0$
#36544590
b1 0
1$
#36586260
0$
#36627930
b10 0
1$
#36669600
0$
#36711270
1/
b0 0
1$
#36752940
0$
#36794610
b1 0
1$
#36836280
0$
#36877950
b10 0
1$
#36919620
0$
#36961290
0/
b0 0
1$
#37002960
0$
#37044630
b1 0
1$
#37086300
0$
#37127970
b10 0
1$
#37169640
0$
#37211310
1/
b0 0
1$
#37252980
0$
#37294650
b1 0
1$
#37336320
0$
#37377990
b10 0
1$
#37419660
0$
#37461330
0/
b0 0
1$
#37503000
0$
#37544670
b1 0
1$
#37586340
0$
#37628010
b10 0
1$
#37669680
0$
#37711350
1/
b0 0
1$
#37753020
0$
#37794690
b1 0
1$
#37836360
0$
#37878030
b10 0
1$
#37919700
0$
#37961370
0/
b0 0
1$
#38003040
0$
#38044710
b1 0
1$
#38086380
0$
#38128050
b10 0
1$
#38169720
0$
#38211390
1/
b0 0
1$
#38253060
0$
#38294730
b1 0
1$
#38336400
0$
#38378070
b10 0
1$
#38419740
0$
#38461410
0/
b0 0
1$
#38503080
0$
#38544750
b1 0
1$
#38586420
0$
#38628090
b10 0
1$
#38669760
0$
#38711430
1/
b0 0
1$
#38753100
0$
#38794770
b1 0
1$
#38836440
0$
#38878110
b10 0
1$
#38919780
0$
#38961450
0/
b0 0
1$
#39003120
0$
#39044790
b1 0
1$
#39086460
0$
#39128130
b10 0
1$
#39169800
0$
#39211470
1/
b0 0
1$
#39253140
0$
#39294810
b1 0
1$
#39336480
0$
#39378150
b10 0
1$
#39419820
0$
#39461490
0/
b0 0
1$
#39503160
0$
#39544830
b1 0
1$
#39586500
0$
#39628170
b10 0
1$
#39669840
0$
#39711510
1/
b0 0
1$
#39753180
0$
#39794850
b1 0
1$
#39836520
0$
#39878190
b10 0
1$
#39919860
0$
#39961530
0/
b0 0
1$
#40003200
0$
#40044870
b1 0
1$
#40086540
0$
#40128210
b10 0
1$
#40169880
0$
#40211550
1/
b0 0
1$
#40253220
0$
#40294890
b1 0
1$
#40336560
0$
#40378230
b10 0
1$
#40419900
0$
#40461570
0/
b0 0
1$
#40503240
0$
#40544910
b1 0
1$
#40586580
0$
#40628250
b10 0
1$
#40669920
0$
#40711590
1/
b0 0
1$
#40753260
0$
#40794930
b1 0
1$
#40836600
0$
#40878270
b10 0
1$
#40919940
0$
#40961610
0/
b0 0
1$
#41003280
0$
#41044950
b1 0
1$
#41086620
0$
#41128290
b10 0
1$
#41169960
0$
#41211630
1/
b0 0
1$
#41253300
0$
#41294970
b1 0
1$
#41336640
0$
#41378310
b10 0
1$
#41419980
0$
#41461650
0/
b0 0
1$
#41503320
0$
#41544990
b1 0
1$
#41586660
0$
#41628330
b10 0
1$
#41670000
0$
#41711670
1/
b0 0
1$
#41753340
0$
#41795010
b1 0
1$
#41836680
0$
#41878350
b10 0
1$
#41920020
0$
#41961690
0/
b0 0
1$
#42003360
0$
#42045030
b1 0
1$
#42086700
0$
#42128370
b10 0
1$
#42170040
0$
#42211710
1/
b0 0
1$
#42253380
0$
#42295050
b1 0
1$
#42336720
0$
