6_function_2LEDs/clock_divider.v
module clock_divider #(
    parameter CLK_ITER_WIDTH                  = 24,
    parameter [CLK_ITER_WIDTH:0] CLK_ITER_MAX = 6000000 - 1
)(
    input clk,        //12MHz clock
    input rst,

    output reg out_clk_div
);
    //parameter CLK_ITER_WIDTH                  = 24;
    //parameter [CLK_ITER_WIDTH:0] CLK_ITER_MAX = 6000000 - 1; //1Hz, factor of 2 from "out_clk_div <= ~out_clk_div"

    reg [CLK_ITER_WIDTH:0] clk_iter;

    always @ (posedge rst or posedge clk) begin
        if (rst == 1'b1) begin
            clk_iter    <= 24'b0;
            out_clk_div <= 0;
        end else if (CLK_ITER_MAX < clk_iter) begin
            clk_iter    <= 24'b0;
            out_clk_div <= ~out_clk_div;
        end else begin 
            clk_iter <= clk_iter + 1;
        end
    end

endmodule

7_sim_clock/main_tb.v
`timescale 1 ns / 10 ps              // set simulated unit / precision

module main_tb();
    wire clkDiv;
    reg clk = 0;
    reg rst = 0;
    localparam SIM_DURATION = 10000;    // in unit of timescale

    //simulation keeps on running the following
    always begin
        #41.667                     //delay by, 1/(2*41.67*1ns) ~ 12MHz of IceStick, round to precision
        clk = ~clk;
    end

    //unit under test (uut), 6/12MHz ~ 0.5us
    clock_divider #(.CLK_ITER_WIDTH(4), .CLK_ITER_MAX(6 - 1)) uut(
        .clk(clk),
        .rst(rst),
        .out_clk_div(clkDiv)
    );

    // pulse reset high at beginning
    initial begin
        #10             //delay by 10*1ns = 10ns 
        rst = 1'b1;
        #1              //delay by 1*1ns = 1ns 
        rst = 1'b0;
    end

    // output file
    initial begin
        $dumpfile("main_tb.vcd");
        $dumpvars(2, main_tb);     //0 verbosity means max verbosity
        #(SIM_DURATION)
        $display("End of Sim.");
        $finish;
    end
endmodule

7_sim_clock/main_tb.vcd
$date
	Sun Jul 28 16:38:16 2024
$end
$version
	Icarus Verilog
$end
$timescale
	1ps
$end
$scope module main_tb $end
$var wire 1 ! clkDiv $end
$var parameter 32 " SIM_DURATION $end
$var reg 1 # clk $end
$var reg 1 $ rst $end
$scope module uut $end
$var wire 1 # clk $end
$var wire 1 $ rst $end
$var parameter 5 % CLK_ITER_MAX $end
$var parameter 32 & CLK_ITER_WIDTH $end
$var reg 5 ' clk_iter [4:0] $end
$var reg 1 ! out_clk_div $end
$upscope $end
$upscope $end
$enddefinitions $end
$comment Show the parameter values. $end
$dumpall
b100 &
b101 %
b10011100010000 "
$end
#0
$dumpvars
bx '
0$
0#
x!
$end
#10000
0!
b0 '
1$
#11000
0$
#41670
b1 '
1#
#83340
0#
#125010
b10 '
1#
#166680
0#
#208350
b11 '
1#
#250020
0#
#291690
b100 '
1#
#333360
0#
#375030
b101 '
1#
#416700
0#
#458370
b110 '
1#
#500040
0#
#541710
1!
b0 '
1#
#583380
0#
#625050
b1 '
1#
#666720
0#
#708390
b10 '
1#
#750060
0#
#791730
b11 '
1#
#833400
0#
#875070
b100 '
1#
#916740
0#
#958410
b101 '
1#
#1000080
0#
#1041750
b110 '
1#
#1083420
0#
#1125090
0!
b0 '
1#
#1166760
0#
#1208430
b1 '
1#
#1250100
0#
#1291770
b10 '
1#
#1333440
0#
#1375110
b11 '
1#
#1416780
0#
#1458450
b100 '
1#
#1500120
0#
#1541790
b101 '
1#
#1583460
0#
#1625130
b110 '
1#
#1666800
0#
#1708470
1!
b0 '
1#
#1750140
0#
#1791810
b1 '
1#
#1833480
0#
#1875150
b10 '
1#
#1916820
0#
#1958490
b11 '
1#
#2000160
0#
#2041830
b100 '
1#
#2083500
0#
#2125170
b101 '
1#
#2166840
0#
#2208510
b110 '
1#
#2250180
0#
#2291850
0!
b0 '
1#
#2333520
0#
#2375190
b1 '
1#
#2416860
0#
#2458530
b10 '
1#
#2500200
0#
#2541870
b11 '
1#
#2583540
0#
#2625210
b100 '
1#
#2666880
0#
#2708550
b101 '
1#
#2750220
0#
#2791890
b110 '
1#
#2833560
0#
#2875230
1!
b0 '
1#
#2916900
0#
#2958570
b1 '
1#
#3000240
0#
#3041910
b10 '
1#
#3083580
0#
#3125250
b11 '
1#
#3166920
0#
#3208590
b100 '
1#
#3250260
0#
#3291930
b101 '
1#
#3333600
0#
#3375270
b110 '
1#
#3416940
0#
#3458610
0!
b0 '
1#
#3500280
0#
#3541950
b1 '
1#
#3583620
0#
#3625290
b10 '
1#
#3666960
0#
#3708630
b11 '
1#
#3750300
0#
#3791970
b100 '
1#
#3833640
0#
#3875310
b101 '
1#
#3916980
0#
#3958650
b110 '
1#
#4000320
0#
#4041990
1!
b0 '
1#
#4083660
0#
#4125330
b1 '
1#
#4167000
0#
#4208670
b10 '
1#
#4250340
0#
#4292010
b11 '
1#
#4333680
0#
#4375350
b100 '
1#
#4417020
0#
#4458690
b101 '
1#
#4500360
0#
#4542030
b110 '
1#
#4583700
0#
#4625370
0!
b0 '
1#
#4667040
0#
#4708710
b1 '
1#
#4750380
0#
#4792050
b10 '
1#
#4833720
0#
#4875390
b11 '
1#
#4917060
0#
#4958730
b100 '
1#
#5000400
0#
#5042070
b101 '
1#
#5083740
0#
#5125410
b110 '
1#
#5167080
0#
#5208750
1!
b0 '
1#
#5250420
0#
#5292090
b1 '
1#
#5333760
0#
#5375430
b10 '
1#
#5417100
0#
#5458770
b11 '
1#
#5500440
0#
#5542110
b100 '
1#
#5583780
0#
#5625450
b101 '
1#
#5667120
0#
#5708790
b110 '
1#
#5750460
0#
#5792130
0!
b0 '
1#
#5833800
0#
#5875470
b1 '
1#
#5917140
0#
#5958810
b10 '
1#
#6000480
0#
#6042150
b11 '
1#
#6083820
0#
#6125490
b100 '
1#
#6167160
0#
#6208830
b101 '
1#
#6250500
0#
#6292170
b110 '
1#
#6333840
0#
#6375510
1!
b0 '
1#
#6417180
0#
#6458850
b1 '
1#
#6500520
0#
#6542190
b10 '
1#
#6583860
0#
#6625530
b11 '
1#
#6667200
0#
#6708870
b100 '
1#
#6750540
0#
#6792210
b101 '
1#
#6833880
0#
#6875550
b110 '
1#
#6917220
0#
#6958890
0!
b0 '
1#
#7000560
0#
#7042230
b1 '
1#
#7083900
0#
#7125570
b10 '
1#
#7167240
0#
#7208910
b11 '
1#
#7250580
0#
#7292250
b100 '
1#
#7333920
0#
#7375590
b101 '
1#
#7417260
0#
#7458930
b110 '
1#
#7500600
0#
#7542270
1!
b0 '
1#
#7583940
0#
#7625610
b1 '
1#
#7667280
0#
#7708950
b10 '
1#
#7750620
0#
#7792290
b11 '
1#
#7833960
0#
#7875630
b100 '
1#
#7917300
0#
#7958970
b101 '
1#
#8000640
0#
#8042310
b110 '
1#
#8083980
0#
#8125650
0!
b0 '
1#
#8167320
0#
#8208990
b1 '
1#
#8250660
0#
#8292330
b10 '
1#
#8334000
0#
#8375670
b11 '
1#
#8417340
0#
#8459010
b100 '
1#
#8500680
0#
#8542350
b101 '
1#
#8584020
0#
#8625690
b110 '
1#
#8667360
0#
#8709030
1!
b0 '
1#
#8750700
0#
#8792370
b1 '
1#
#8834040
0#
#8875710
b10 '
1#
#8917380
0#
#8959050
b11 '
1#
#9000720
0#
#9042390
b100 '
1#
#9084060
0#
#9125730
b101 '
1#
#9167400
0#
#9209070
b110 '
1#
#9250740
0#
#9292410
0!
b0 '
1#
#9334080
0#
#9375750
b1 '
1#
#9417420
0#
#9459090
b10 '
1#
#9500760
0#
#9542430
b11 '
1#
#9584100
0#
#9625770
b100 '
1#
#9667440
0#
#9709110
b101 '
1#
#9750780
0#
#9792450
b110 '
1#
#9834120
0#
#9875790
1!
b0 '
1#
#9917460
0#
#9959130
b1 '
1#
